<PigmendPlayer>
	<SoftwareName>Pigmend Player</SoftwareName>
	<SoftwareURL>https://github.com/septimomend/pigmend-player</SoftwareURL>
	<Version>1.3</Version>
	<Author>
		<Name>Ivan Chapkailo</Name>
		<URL>https://github.com/septimomend/</URL>
	</Author>
	<Year>2022</Year>
	<Description>NULL</Description>
	<Contributors>NULL</Contributors>
	<Libs>RapidXML, TinyXML2, TagLib</Libs>
	<Sources>NULL</Sources>
	<Resources>NULL</Resources>
	<Releases>
		<Release id="1">
			<Version>1.0</Version>
			<URL>https://github.com/septimomend/pigmend-player/releases/tag/v1.0</URL>
		</Release>
	</Releases>
</PigmendPlayer>
